<?xml version="1.0" encoding="UTF-8"?>
<databaseChangeLog
        xmlns="http://www.liquibase.org/xml/ns/dbchangelog"
        xmlns:xsi="http://www.w3.org/2001/XMLSchema-instance"
        xsi:schemaLocation="http://www.liquibase.org/xml/ns/dbchangelog http://www.liquibase.org/xml/ns/dbchangelog/dbchangelog-3.1.xsd">
    <!-- Создание таблицы role и заполнение полей Ролей  -->
        <changeSet id="1" author="maksim">
        <createTable tableName="role">
            <column name="id" type="int" autoIncrement="true">
                <constraints primaryKey="true" nullable="false"/>
            </column>
            <column name="role" type="varchar(50)">
                <constraints nullable="false"/>
            </column>
        </createTable>
        </changeSet>
        <changeSet id="2" author="maksim">
            <insert tableName="role">
                <column name="id" value="1"/>
                <column name="role" value="admin"/>
            </insert>
            <insert tableName="role">
                <column name="id" value="2"/>
                <column name="role" value="user"/>
            </insert>
        </changeSet>
    <!--//////////////////////////////////////////////////////-->

    <!-- Создание таблицы users и заполнение полей для User  -->
        <changeSet id="3" author="maksim">
            <createTable tableName="users">
                <column name="id" type="int" autoIncrement="true">
                    <constraints primaryKey="true" nullable="false"/>
                </column>
                <column name="login" type="varchar">
                    <constraints nullable="false"/>
                </column>
                <column name="password" type="varchar">
                    <constraints nullable="false"/>
                </column>
                <column name="email" type="varchar">
                    <constraints nullable="false"/>
                </column>
                <column name="enabled" type="boolean">
                    <constraints nullable="false"/>
                </column>
                <!--column name="role" type="int">
                    <constraints nullable="false"/>
                </column-->
            </createTable>
        </changeSet>
        <changeSet id="4" author="maksim">
            <insert tableName="users">
                <column name="login" value="admin"/>
                <column name="password" value="admin"/>
                <column name="email" value="admin@mail.ru"/>
                <column name="enabled" value="true"/>

            </insert>
            <insert tableName="users">
                <column name="login" value="one"/>
                <column name="password" value="one"/>
                <column name="email" value="one@mail.ru"/>
                <column name="enabled" value="true"/>

            </insert>
            <insert tableName="users">
                <column name="login" value="two"/>
                <column name="password" value="two"/>
                <column name="email" value="two@mail.ru"/>
                <column name="enabled" value="true"/>

            </insert>
            <insert tableName="users">
                <column name="login" value="three"/>
                <column name="password" value="three"/>
                <column name="email" value="three@mail.ru"/>
                <column name="enabled" value="true"/>

            </insert>
            <insert tableName="users">
                <column name="login" value="fore"/>
                <column name="password" value="fore"/>
                <column name="email" value="fore@mail.ru"/>
                <column name="enabled" value="true"/>

            </insert>
            <insert tableName="users">
                <column name="login" value="five"/>
                <column name="password" value="five"/>
                <column name="email" value="five@mail.ru"/>
                <column name="enabled" value="true"/>

            </insert>

            <insert tableName="users">
                <column name="login" value="max"/>
                <column name="password" value="max"/>
                <column name="email" value="max@mail.ru"/>
                <column name="enabled" value="true"/>
            </insert>

        </changeSet>
    <!--//////////////////////////////////////////////////////-->
    <!-- Создание таблицы message_status и заполнение полей для messageStatus -->
        <changeSet id="5" author="maksim">
            <createTable tableName="message_status">
                <column name="id" type="int" autoIncrement="true">
                    <constraints primaryKey="true" nullable="false"/>
                </column>
                <column name="status" type="varchar(50)">
                    <constraints nullable="false"/>
                </column>
            </createTable>
        </changeSet>
        <changeSet id="6" author="maksim">
            <insert tableName="message_status">
                <column name="id" value="1"/>
                <column name="status" value="send"/>
            </insert>
            <insert tableName="message_status">
                <column name="id" value="2"/>
                <column name="status" value="received"/>
            </insert>
        </changeSet>
    <!--/////////////////////////////////////////////////////-->
    <!-- Создание таблицы message_type и заполнение полей для type  -->
        <changeSet id="7" author="maksim">
            <createTable tableName="message_type">
                <column name="id" type="int" autoIncrement="true">
                    <constraints primaryKey="true" nullable="false"/>
                </column>
                <column name="type" type="varchar(50)">
                    <constraints nullable="false"/>
                </column>
            </createTable>
        </changeSet>
        <changeSet id="8" author="maksim">
            <insert tableName="message_type">
                <column name="id" value="1"/>
                <column name="type" value="normal"/>
            </insert>
            <insert tableName="message_type">
                <column name="id" value="2"/>
                <column name="type" value="order"/>
            </insert>
        </changeSet>
    <!--/////////////////////////////////////////////////////-->
    <!-- Создание таблицы message и заполнение полей для mail -->
    <changeSet id="9" author="maksim">
        <createTable tableName="message">
            <column name="id" type="int" autoIncrement="true">
                <constraints primaryKey="true" nullable="false"/>
            </column>
            <column name="text_message" type="varchar">
                <constraints nullable="false"/>
            </column>
            <column name="user_to" type="int">
                <constraints nullable="false"/>
            </column>
            <column name="user_from" type="int">
                <constraints nullable="false"/>
            </column>
            <column name="message_type" type="int">
                <constraints nullable="false"/>
            </column>
            <column name="date_send" type="datetime">
                <constraints nullable="true"/>
            </column>
            <column name="date_get" type="datetime">
                <constraints nullable="true"/>
            </column>
        </createTable>
    </changeSet>
    <changeSet id="10" author="maksim">
        <insert tableName="message">
            <column name="id" value="1"/>
            <column name="text_message" value="Добрый вечер как дела?"/>
            <column name="user_to" value="1"/>
            <column name="user_from" value="2"/>
            <column name="message_type" value="1"/>
            <column name="date_send" value="10.12.2012"/>
            <column name="date_get" value="14.12.2012"/>
        </insert>
        <insert tableName="message">
            <column name="id" value="2"/>
            <column name="text_message" value="Добрый вечер как дела?"/>
            <column name="user_to" value="1"/>
            <column name="user_from" value="3"/>
            <column name="message_type" value="1"/>
            <column name="date_send" value="10.12.2012"/>
            <column name="date_get" value="14.12.2012"/>
        </insert>
        <insert tableName="message">
            <column name="id" value="3"/>
            <column name="text_message" value="Добрый вечер как дела?"/>
            <column name="user_to" value="2"/>
            <column name="user_from" value="4"/>
            <column name="message_type" value="1"/>
            <column name="date_send" value="10.12.2012"/>
            <column name="date_get" value="14.12.2012"/>
        </insert>
        <insert tableName="message">
            <column name="id" value="4"/>
            <column name="text_message" value="Добрый вечер как дела?"/>
            <column name="user_to" value="1"/>
            <column name="user_from" value="2"/>
            <column name="message_type" value="2"/>
            <column name="date_send" value="10.12.2012"/>
            <column name="date_get" value="14.12.2012"/>
        </insert>
        <insert tableName="message">
            <column name="id" value="5"/>
            <column name="text_message" value="Добрый вечер как дела?"/>
            <column name="user_to" value="1"/>
            <column name="user_from" value="2"/>
            <column name="message_type" value="2"/>
            <column name="date_send" value="10.12.2012"/>
            <column name="date_get" value="14.12.2012"/>
        </insert>
        <insert tableName="message">
            <column name="id" value="6"/>
            <column name="text_message" value="Добрый вечер как дела?"/>
            <column name="user_to" value="1"/>
            <column name="user_from" value="2"/>
            <column name="message_type" value="1"/>
            <column name="date_send" value="10.12.2012"/>
            <column name="date_get" value="14.12.2012"/>
        </insert>
    </changeSet>
    <!--/////////////////////////////////////////////////////-->
    <!-- Создание таблицы role и заполнение полей для mail -->
    <changeSet id="11" author="maksim">
        <createTable tableName="user_role">
            <column name="id" type="int">
                <constraints primaryKey="true" nullable="false"/>
            </column>
            <column name="role" type="varchar">
                <constraints nullable="false"/>
            </column>
        </createTable>
    </changeSet>
    <changeSet id="12" author="maksim">
        <insert tableName="user_role">
            <column name="id" value="1"/>
            <column name="role" value="ADMIN"/>
        </insert>
        <insert tableName="user_role">
            <column name="id" value="2"/>
            <column name="role" value="USER"/>
        </insert>
        <insert tableName="user_role">
            <column name="id" value="3"/>
            <column name="role" value="USER"/>
        </insert>
        <insert tableName="user_role">
            <column name="id" value="4"/>
            <column name="role" value="USER"/>
        </insert>
        <insert tableName="user_role">
            <column name="id" value="5"/>
            <column name="role" value="USER"/>
        </insert>
        <insert tableName="user_role">
            <column name="id" value="6"/>
            <column name="role" value="USER"/>
        </insert>
        <insert tableName="user_role">
            <column name="id" value="7"/>
            <column name="role" value="USER"/>
        </insert>
    </changeSet>
    <!--//////////////////////////////////////////////////////-->
</databaseChangeLog>
